<?xml version="1.0" encoding="UTF-8"?>
<databaseChangeLog
  xmlns="http://www.liquibase.org/xml/ns/dbchangelog"
  xmlns:xsi="http://www.w3.org/2001/XMLSchema-instance"
  xsi:schemaLocation="http://www.liquibase.org/xml/ns/dbchangelog
          http://www.liquibase.org/xml/ns/dbchangelog/dbchangelog-4.27.xsd">


  <changeSet id="86ev6ae1a_1" author="glohow-dean" labels="sprint-38" runOnChange="false">
    <comment>Drop 'lastReadAt' in Subscriber</comment>
    <sqlFile path="86ev6ae1a-DropLastReadAtInSubscriber.sql"
             relativeToChangelogFile="true"
             endDelimiter=";"
             splitStatements="false"
             stripComments="true"/>
  </changeSet>

  <changeSet id="86ev6ae1a_2" author="glohow-dean" labels="sprint-38" runOnChange="false">
    <comment>Drop 'readOverride' in Notification Message</comment>
    <sqlFile path="86ev6ae1a-DropReadOverrideInNotificationMessage.sql"
             relativeToChangelogFile="true"
             endDelimiter=";"
             splitStatements="false"
             stripComments="true"/>
  </changeSet>

</databaseChangeLog>
